README.md
setup.py
RedaTade/__init__.py
RedaTade/set.py
RedaTade.egg-info/PKG-INFO
RedaTade.egg-info/SOURCES.txt
RedaTade.egg-info/dependency_links.txt
RedaTade.egg-info/requires.txt
RedaTade.egg-info/top_level.txt