Metadata-Version: 2.1
Name: RedaTade
Version: 1.0.0
Summary: Stats and Config Library for Challenge Bot
Author: Reda
Classifier: Programming Language :: Python :: 3
Classifier: License :: OSI Approved :: MIT License
Classifier: Operating System :: OS Independent
Requires-Python: >=3.6
Requires-Dist: requests
